unstract/api_deployments/__init__.py
unstract/api_deployments/client.py
unstract/api_deployments/utils.py
unstract_client-1.1.0.dist-info/METADATA
unstract_client-1.1.0.dist-info/WHEEL
unstract_client-1.1.0.dist-info/entry_points.txt
unstract_client-1.1.0.dist-info/licenses/LICENSE
unstract_client-1.1.0.dist-info/RECORD
