Metadata-Version: 2.1
Name: unstract-client
Version: 1.1.0
Summary: Python client for the Unstract LLM-powered structured data extraction platform
Keywords: unstract cli apps sdk
Author-Email: Zipstack Inc <devsupport@zipstack.com>
License: MIT
Classifier: Development Status :: 4 - Beta
Classifier: Intended Audience :: Developers
Classifier: License :: OSI Approved :: MIT License
Classifier: Operating System :: POSIX :: Linux
Classifier: Operating System :: MacOS :: MacOS X
Classifier: Operating System :: Microsoft :: Windows
Classifier: Programming Language :: Python
Classifier: Topic :: Software Development :: Libraries :: Python Modules
Project-URL: Homepage, https://unstract.com
Project-URL: Source, https://github.com/Zipstack/unstract-python-client
Requires-Python: >=3.11
Requires-Dist: requests>=2.32.3
